_gdxcc.cpython-311-x86_64-linux-gnu.so
gdxcc/gdxcc.py
gdxcc/__init__.py
gdxcc/gdxcc.i
gdxcc/C/gcmt.h
gdxcc/C/gcmt.c
gdxcc/C/gdxcc_wrap.c
gdxcc/C/gclgms.c
gdxcc/C/gdxcc.h
gdxcc/C/gdxcc.c
gdxcc/C/gclgms.h
gdxcc-8.33.2.post1.dist-info/METADATA
gdxcc-8.33.2.post1.dist-info/LICENSE
gdxcc-8.33.2.post1.dist-info/WHEEL
gdxcc-8.33.2.post1.dist-info/top_level.txt
gdxcc-8.33.2.post1.dist-info/RECORD
