Metadata-Version: 2.1
Name: gdxcc
Version: 8.33.2.post1
Summary: Python library to access and modify gdx files
Home-page: https://github.com/kavvkon/gams-api
Author: GAMS Development Corp.
Maintainer: kavvkon
Maintainer-email: kavvkon@gmail.com
License: MIT
License-File: LICENSE
